setup.py
amathon/__init__.py
amathon/amathon.py
amathon/binder.py
amathon.egg-info/PKG-INFO
amathon.egg-info/SOURCES.txt
amathon.egg-info/dependency_links.txt
amathon.egg-info/top_level.txt