Metadata-Version: 1.0
Name: amathon
Version: 0.2
Summary: Amazon api wrapper for Python 3.x
Home-page: https://github.com/y42sora/Amathon
Author: y42sora (http://y42sora.com)
Author-email: UNKNOWN
License: LGPL
Keywords: amazon,python3
Platform: UNKNOWN
Classifier: Development Status :: 3 - Alpha
Classifier: Intended Audience :: Developers
Classifier: License :: OSI Approved :: GNU Library or Lesser General Public License (LGPL)
Classifier: Programming Language :: Python
Classifier: Topic :: Software Development :: Libraries :: Python Modules
